ibats_common/__init__.py
ibats_common/common.py
ibats_common/config.py
ibats_common/event.py
ibats_common/md.py
ibats_common/strategy.py
ibats_common/strategy_handler.py
ibats_common/trade.py
ibats_common/analysis/__init__.py
ibats_common/analysis/plot.py
ibats_common/analysis/plot_db.py
ibats_common/analysis/summary.py
ibats_common/backend/__init__.py
ibats_common/backend/factor.py
ibats_common/backend/factor_analysis.py
ibats_common/backend/label.py
ibats_common/backend/mess.py
ibats_common/backend/orm.py
ibats_common/backend/stat_utils.py
ibats_common/backend/xy.py
ibats_common/backend/rl/__init__.py
ibats_common/backend/rl/utils.py
ibats_common/backend/rl/emulator/__init__.py
ibats_common/backend/rl/emulator/account.py
ibats_common/backend/rl/emulator/market.py
ibats_common/backend/rl/emulator/market2.py
ibats_common/example/__init__.py
ibats_common/example/abitrage_stg.py
ibats_common/example/ma_cross_stg.py
ibats_common/example/ma_cross_stg_fix.py
ibats_common/example/data/__init__.py
ibats_common/example/rl_stg/__init__.py
ibats_common/example/rl_stg/v3/__init__.py
ibats_common/example/rl_stg/v3/q_learn.py
ibats_common/example/rl_stg/v3/rl_stg.py
ibats_common/example/tf_stg/__init__.py
ibats_common/example/tf_stg/ai_3_stg.py
ibats_common/example/tf_stg/ai_stg.py
ibats_common/test/__init__.py
ibats_common/test/orm_init_test.py
ibats_common/test/orm_pos_status_detail_test.py
ibats_common/test/orm_stg_run_status_detail_test.py
ibats_common/test/orm_trade_agent_detail_test.py
ibats_common/test/orm_trade_detail_test.py
ibats_common/test/plot2_test.py
ibats_local_trader/__init__.py
ibats_local_trader/config.py
ibats_local_trader/agent/__init__.py
ibats_local_trader/agent/md_agent.py
ibats_local_trader/agent/td_agent.py
IBATS_Common-0.20.11.dist-info/LICENSE
IBATS_Common-0.20.11.dist-info/METADATA
IBATS_Common-0.20.11.dist-info/WHEEL
IBATS_Common-0.20.11.dist-info/top_level.txt
IBATS_Common-0.20.11.dist-info/RECORD
