Metadata-Version: 2.1
Name: IBATS-Common
Version: 0.20.11
Summary: IBATS（Integration Backtest Analysis Trade System）的公共模块，所有Feeder, Trader均集成这个模块，并使用其提供的一些公共工具
Home-page: https://github.com/IBATS/IBATS_Common
Author: MG
Author-email: mmmaaaggg@163.com
License: UNKNOWN
Platform: UNKNOWN
Classifier: Programming Language :: Python :: 3 :: Only
Classifier: Programming Language :: Python :: 3.6
Classifier: Programming Language :: Python :: 3.7
Classifier: Programming Language :: Python :: 3.8
Classifier: Operating System :: Microsoft :: Windows
Classifier: Operating System :: Unix
Classifier: Operating System :: POSIX
Classifier: License :: OSI Approved :: MIT License
Classifier: Development Status :: 5 - Production/Stable
Classifier: Environment :: No Input/Output (Daemon)
Classifier: Intended Audience :: Developers
Classifier: Natural Language :: Chinese (Simplified)
Classifier: Topic :: Software Development
Requires-Python: >=3.6
License-File: LICENSE
Requires-Dist: IBATS-Utils (>=1.2.12)
Requires-Dist: numpy (>=1.20.3)
Requires-Dist: pandas (>=0.25.0)
Requires-Dist: scipy (>=1.4.1)
Requires-Dist: statsmodels (>=0.11.1)
Requires-Dist: redis (>=2.10.6)
Requires-Dist: SQLAlchemy (>=1.3.2)
Requires-Dist: mysqlclient (>=1.4.6)
Requires-Dist: xlrd (>=1.1.0)
Requires-Dist: matplotlib (>=3.3.0)
Requires-Dist: seaborn (>=0.9)
Requires-Dist: ffn (>=0.3.6)
Requires-Dist: python-docx (>=0.8.10)
Requires-Dist: TA-Lib (>=0.4.17)
Requires-Dist: factor-analyzer (>=0.3.2)
